dune_aws/__init__.py
dune_aws/aws.py
dune_aws/environment.py
dune_aws/logger.py
dune_aws/py.typed
dune_aws/record_handler.py
dune_aws/text_io.py
dune_aws-0.0.0b0.dist-info/METADATA
dune_aws-0.0.0b0.dist-info/WHEEL
dune_aws-0.0.0b0.dist-info/top_level.txt
dune_aws-0.0.0b0.dist-info/RECORD
