Metadata-Version: 2.1
Name: dune-aws
Version: 0.0.0b0
Summary: Python Package for Uploading Data to Dune Community Sources
Home-page: https://github.com/bh2smith/dune-aws
Author: Benjamin H. Smith
Author-email: ben@cow.fi
License: Apache License Version 2.0
Project-URL: Tracker, https://github.com/bh2smith/dune-aws/issues
Classifier: Programming Language :: Python :: 3
Classifier: License :: OSI Approved :: Apache Software License
Classifier: Operating System :: OS Independent
Requires-Python: >=3.10
Requires-Dist: types-requests (>=2.28.9)
Requires-Dist: python-dotenv (>=0.20.0)
Requires-Dist: requests (>=2.28.1)
Requires-Dist: boto3 (>=1.26.12)
